geode_common/__init__.py
geode_common/__init__.pyi
geode_common/core_common.py
geode_common/core_common.pyi
geode_common/cutter_model.py
geode_common/cutter_model.pyi
geode_common/cutter_solid.py
geode_common/cutter_solid.pyi
geode_common/cutter_surface.py
geode_common/cutter_surface.pyi
geode_common/helpers_common.py
geode_common/helpers_common.pyi
geode_common/metric_common.py
geode_common/metric_common.pyi
geode_common/modifier_edged_curve.py
geode_common/modifier_edged_curve.pyi
geode_common/modifier_model.py
geode_common/modifier_model.pyi
geode_common/modifier_point_set.py
geode_common/modifier_point_set.pyi
geode_common/modifier_solid.py
geode_common/modifier_solid.pyi
geode_common/modifier_surface.py
geode_common/modifier_surface.pyi
geode_common/orchestrator_common.py
geode_common/orchestrator_common.pyi
geode_common/orchestrator_model.py
geode_common/orchestrator_model.pyi
geode_common/orchestrator_solid.py
geode_common/orchestrator_solid.pyi
geode_common/orchestrator_surface.py
geode_common/orchestrator_surface.pyi
geode_common/py.typed
geode_common/bin/Geode-Common_cutter_model.dll
geode_common/bin/Geode-Common_cutter_solid.dll
geode_common/bin/Geode-Common_cutter_surface.dll
geode_common/bin/Geode-Common_helpers.dll
geode_common/bin/Geode-Common_metric.dll
geode_common/bin/Geode-Common_modifier_common.dll
geode_common/bin/Geode-Common_modifier_edged_curve.dll
geode_common/bin/Geode-Common_modifier_graph.dll
geode_common/bin/Geode-Common_modifier_model.dll
geode_common/bin/Geode-Common_modifier_point_set.dll
geode_common/bin/Geode-Common_modifier_solid.dll
geode_common/bin/Geode-Common_modifier_surface.dll
geode_common/bin/Geode-Common_orchestrator_common.dll
geode_common/bin/Geode-Common_orchestrator_model.dll
geode_common/bin/Geode-Common_orchestrator_solid.dll
geode_common/bin/Geode-Common_orchestrator_surface.dll
geode_common/bin/__init__.pyi
geode_common/bin/geode_common_py_core.cp39-win_amd64.pyd
geode_common/bin/geode_common_py_core.pyi
geode_common-33.16.4.dist-info/METADATA
geode_common-33.16.4.dist-info/WHEEL
geode_common-33.16.4.dist-info/top_level.txt
geode_common-33.16.4.dist-info/RECORD
