Metadata-Version: 2.4
Name: Geode-Common
Version: 33.16.4
Summary: Common module for licensed Geode-solutions modules
Author-email: Geode-solutions <contact@geode-solutions.com>
License: Proprietary
Requires-Python: <3.13,>=3.9
Requires-Dist: opengeode-core==15.*,>=15.30.16
